Metadata-Version: 2.1
Name: pykit-bsc
Version: 0.0.5
Summary: A collection of toolkit lib for distributed system development in python
Home-page: https://github.com/bsc-s2/pykit
Author: Zhang Yanpo
Author-email: drdr.xp@gmail.com
License: MIT
Platform: UNKNOWN
Classifier: Programming Language :: Python :: 2.7
Classifier: License :: OSI Approved :: MIT License
Classifier: Operating System :: OS Independent
Requires-Python: >=2.7
Requires-Dist: pyflakes
Requires-Dist: autopep8
Requires-Dist: autoflake
Requires-Dist: isort
Requires-Dist: psutil (==4.3.1)
Requires-Dist: netifaces (==0.10.6)
Requires-Dist: tzlocal (==1.5.1)
Requires-Dist: pytz (==2018.4)
Requires-Dist: docker-py (==1.10.6)
Requires-Dist: subprocess32 (==3.2.7)
Requires-Dist: kazoo (==2.2.1)
Requires-Dist: snakefood
Requires-Dist: gevent (==1.3.0)
Requires-Dist: redis (==2.10.6)
Requires-Dist: PyYAML (==3.12)
